pfs_mcdm/__init__.py
pfs_mcdm/mcdm.py
pfs_mcdm/pfn.py
pfs_mcdm/promethee.py
pfs_mcdm/simple_aggregation.py
pfs_mcdm/topsis.py
pfs_mcdm-0.2.dist-info/LICENSE
pfs_mcdm-0.2.dist-info/METADATA
pfs_mcdm-0.2.dist-info/WHEEL
pfs_mcdm-0.2.dist-info/top_level.txt
pfs_mcdm-0.2.dist-info/RECORD
