Metadata-Version: 2.1
Name: pfs-mcdm
Version: 0.2
Summary: Multi-Criteria Decision Making using Pythagorean Fuzzy Sets
Author-email: Khaled Janada <khaledjanada@gmail.com>
License: MIT
Project-URL: Homepage, https://github.com/Khaled-Janada/pfs-mcdm
Classifier: Programming Language :: Python :: 3.9
Classifier: License :: OSI Approved :: MIT License
Classifier: Operating System :: OS Independent
Classifier: Topic :: Scientific/Engineering
Requires-Python: >=3.9
License-File: LICENSE
Requires-Dist: pandas
